README.md
setup.py
transportmodels/__init__.py
transportmodels/test.py
transportmodels/trans.py
transportmodels.egg-info/PKG-INFO
transportmodels.egg-info/SOURCES.txt
transportmodels.egg-info/dependency_links.txt
transportmodels.egg-info/not-zip-safe
transportmodels.egg-info/top_level.txt