Metadata-Version: 1.1
Name: transportmodels
Version: 0.1.0
Summary: Solve the balanced transportation problem with LP (using ortools).
Home-page: https://github.com/xianqiu/TransportModels
Author: qx3501332
Author-email: x.qiu@qq.com
License: MIT License
Platform: UNKNOWN
Classifier: Development Status :: 4 - Beta
Classifier: Intended Audience :: Developers
Classifier: Operating System :: OS Independent
Classifier: Programming Language :: Python :: 3.6
Classifier: Topic :: Software Development :: Libraries :: Python Modules
